LICENCE
MANIFEST.in
README.rst
grind.py
setup.py
grind.egg-info/PKG-INFO
grind.egg-info/SOURCES.txt
grind.egg-info/dependency_links.txt
grind.egg-info/entry_points.txt
grind.egg-info/requires.txt
grind.egg-info/top_level.txt