Metadata-Version: 1.1
Name: grind
Version: 0.2.0
Summary: delegate tasks to EC2 spot instances
Home-page: http://github.com/3kwa/grind
Author: Eugene Van den Bulke
Author-email: eugene.vandenbulke@gmail.com
License: BSD
Platform: UNKNOWN
Classifier: Development Status :: 3 - Alpha
Classifier: License :: OSI Approved :: BSD License
Classifier: Programming Language :: Python :: 2.7
